speed_stack/__init__.py
speed_stack-0.1.1.dist-info/WHEEL
speed_stack-0.1.1.dist-info/METADATA
speed_stack-0.1.1.dist-info/RECORD
